aul/__init__.py
aul/core.py
aul-0.1.2.dist-info/LICENSE
aul-0.1.2.dist-info/METADATA
aul-0.1.2.dist-info/WHEEL
aul-0.1.2.dist-info/top_level.txt
aul-0.1.2.dist-info/RECORD
