Metadata-Version: 2.1
Name: aul
Version: 0.1.2
Summary: A package to export NetLogo model runs in GIF or MP4 formats
Home-page: https://github.com/steipatr/aul
Author: Patrick Steinmann
Author-email: patrick.steinmann@wur.nl
License: UNKNOWN
Platform: UNKNOWN
Classifier: Programming Language :: Python :: 3
Classifier: License :: OSI Approved :: BSD License
Classifier: Operating System :: OS Independent
Requires-Python: >=3.6
